{
  "updated_at": "2026-07-08T10:30:00+08:00",
  "source_health": {
    "healthy": 20,
    "total": 20
  },
  "items": [
    {
      "id": "20260708-001",
      "rank": 1,
      "category": "policy",
      "source": "SAMR",
      "source_count": 1,
      "priority": "A",
      "published_at": "2026-07-08T08:00:00+08:00",
      "title": "市场监管总局特殊食品注册信息查询入口仍是保健食品合规核验的第一站",
      "summary": "市场监管总局政务服务平台持续提供特殊食品注册信息查询入口，可用于核对保健食品注册证书、产品名称、企业主体和批准信息。对大健康内容团队而言，这类入口比二手招商文案更适合作为选品、科普和合规审核的底层链接。",
      "detail": "这是市场监管总局政务服务平台的特殊食品注册信息查询入口，面向公众提供保健食品等特殊食品注册信息核验。它不是单条新闻，而是每天筛查产品资质和宣传素材时应优先打开的官方数据库。 行业信号是保健食品内容生产正在从讲卖点转向讲证据和资质。只引用产品海报或平台招商页，无法证明批准范围、适用人群和注册信息，容易把普通食品、保健食品和药品边界混在一起。 从业者应把该入口做成选题前置检查清单：先查注册信息，再写功效边界，再核对标签和广告语。消费者向内容可改写成“买保健食品前先查这 3 个信息”，但不能把查询结果解释成医学干预或适合所有人的保证。",
      "key_points": [
        {
          "label": "这是什么",
          "text": "这是市场监管总局政务服务平台的特殊食品注册信息查询入口，面向公众提供保健食品等特殊食品注册信息核验。它不是单条新闻，而是每天筛查产品资质和宣传素材时应优先打开的官方数据库。"
        },
        {
          "label": "行业信号或健康要点",
          "text": "行业信号是保健食品内容生产正在从讲卖点转向讲证据和资质。只引用产品海报或平台招商页，无法证明批准范围、适用人群和注册信息，容易把普通食品、保健食品和药品边界混在一起。"
        },
        {
          "label": "从业者或消费者启发",
          "text": "从业者应把该入口做成选题前置检查清单：先查注册信息，再写功效边界，再核对标签和广告语。消费者向内容可改写成“买保健食品前先查这 3 个信息”，但不能把查询结果解释成医学干预或适合所有人的保证。"
        }
      ],
      "why": "官方查询入口能降低保健食品二创内容的源头风险。",
      "media_potential": "适合做《保健食品资质怎么查：普通消费者也能用的官方入口》。",
      "compliance_note": "只说明查询和核验方法，不扩大为产品疗效背书。",
      "consumer_angle": "消费者可学会看注册证书、产品名称、企业主体和批准范围。",
      "rewrite_formats": [
        "公众号科普",
        "短视频清单",
        "社群问答",
        "合规培训"
      ],
      "safe_claims": [
        "可以建议使用官方入口核验资质",
        "可以提醒核对产品名称和批准范围",
        "可以说明查询结果不等于疗效保证"
      ],
      "avoid_claims": [
        "宣称查到注册就一定有效",
        "把保健食品写成药品",
        "替具体产品做疗效承诺"
      ],
      "evidence_level": "官方监管数据库",
      "tags": [
        "保健食品",
        "特殊食品",
        "市场监管",
        "资质核验"
      ],
      "url": "https://zwfw.samr.gov.cn/spsp/spspindex/index.xhtml"
    },
    {
      "id": "20260708-002",
      "rank": 2,
      "category": "policy",
      "source": "SAMR",
      "source_count": 1,
      "priority": "A",
      "published_at": "2026-07-08T08:00:00+08:00",
      "title": "食品安全抽检信息提示健康食品团队把供应链风险纳入日常内容",
      "summary": "市场监管系统食品安全抽检通告持续披露不合格项目、样品类别和处置要求。对大健康从业者来说，抽检不是单纯负面新闻，而是判断原料、标签、批次管理和售后响应的重要样本。",
      "detail": "这是市场监管部门持续发布的食品安全抽检信息，覆盖食用农产品、预包装食品、特殊食品相关类别等。每一条抽检信息都应回到具体样品、批次、检验项目和处置要求，而不是停留在标题。 行业信号是食品安全监管越来越依赖公开抽检和批次追踪。健康食品团队如果只讲营养概念，不理解抽检项目、标签问题和供应链处置，内容和经营都会留下风险。 从业者可将抽检通告改写成内部风控清单：看批次、看项目、看召回或下架要求。消费者内容可讲“看到抽检通告该怎么看”，避免把个案扩大成整个品类不安全。",
      "key_points": [
        {
          "label": "这是什么",
          "text": "这是市场监管部门持续发布的食品安全抽检信息，覆盖食用农产品、预包装食品、特殊食品相关类别等。每一条抽检信息都应回到具体样品、批次、检验项目和处置要求，而不是停留在标题。"
        },
        {
          "label": "行业信号或健康要点",
          "text": "行业信号是食品安全监管越来越依赖公开抽检和批次追踪。健康食品团队如果只讲营养概念，不理解抽检项目、标签问题和供应链处置，内容和经营都会留下风险。"
        },
        {
          "label": "从业者或消费者启发",
          "text": "从业者可将抽检通告改写成内部风控清单：看批次、看项目、看召回或下架要求。消费者内容可讲“看到抽检通告该怎么看”，避免把个案扩大成整个品类不安全。"
        }
      ],
      "why": "抽检通告是食品和营养产品供应链风险的官方样本。",
      "media_potential": "适合做《食品抽检通告怎么读：别只看不合格三个字》。",
      "compliance_note": "必须限定在公告列明事实，不点名未涉及品牌。",
      "consumer_angle": "消费者可学习核对批次、检验项目和官方处置说明。",
      "rewrite_formats": [
        "公众号解读",
        "风险清单",
        "短视频科普",
        "社群提醒"
      ],
      "safe_claims": [
        "可以引用官方抽检事实",
        "可以提醒核对批次",
        "可以解释不合格项目含义"
      ],
      "avoid_claims": [
        "制造恐慌",
        "扩大到未涉及品类",
        "用抽检结论攻击竞品"
      ],
      "evidence_level": "官方监管通告",
      "tags": [
        "食品安全",
        "抽检",
        "供应链",
        "标签合规"
      ],
      "url": "https://zwfw.samr.gov.cn/"
    },
    {
      "id": "20260708-003",
      "rank": 3,
      "category": "policy",
      "source": "NMPA",
      "source_count": 1,
      "priority": "A",
      "published_at": "2026-07-08T08:00:00+08:00",
      "title": "药监部门医疗器械注册公告提醒健康硬件必须先判断监管属性",
      "summary": "国家药监局医疗器械注册公告持续披露获批产品和注册信息。可穿戴、血糖血压、睡眠监测、康复设备等健康硬件在内容传播前，应先判断是否落入医疗器械监管边界。",
      "detail": "这是国家药监局医疗器械注册公告和查询体系中的信息，核心价值是帮助核对产品注册类别、适用范围和注册人。健康硬件并不因为面向家庭使用就自动变成普通消费电子。 行业信号是家用健康硬件与医疗器械边界仍在收紧。越是涉及监测、辅助诊断、康复和慢病管理的产品，越需要把注册证、适用范围和说明书作为内容依据。 从业者应在写“健康管理设备”前先查注册属性，避免把未获批用途包装成诊断能力。消费者内容可改写成“买家用检测设备前看清 4 件事”。",
      "key_points": [
        {
          "label": "这是什么",
          "text": "这是国家药监局医疗器械注册公告和查询体系中的信息，核心价值是帮助核对产品注册类别、适用范围和注册人。健康硬件并不因为面向家庭使用就自动变成普通消费电子。"
        },
        {
          "label": "行业信号或健康要点",
          "text": "行业信号是家用健康硬件与医疗器械边界仍在收紧。越是涉及监测、辅助诊断、康复和慢病管理的产品，越需要把注册证、适用范围和说明书作为内容依据。"
        },
        {
          "label": "从业者或消费者启发",
          "text": "从业者应在写“健康管理设备”前先查注册属性，避免把未获批用途包装成诊断能力。消费者内容可改写成“买家用检测设备前看清 4 件事”。"
        }
      ],
      "why": "医疗器械注册信息决定健康硬件传播边界。",
      "media_potential": "适合做《健康手环、血压计、睡眠仪：哪些话不能乱说》。",
      "compliance_note": "不得宣称未获批诊断、医学干预或康复效果。",
      "consumer_angle": "消费者可学习看注册证编号、适用范围和说明书限制。",
      "rewrite_formats": [
        "合规培训",
        "公众号科普",
        "短视频清单",
        "选品核验"
      ],
      "safe_claims": [
        "可以提示查询注册信息",
        "可以说明适用范围要以说明书为准",
        "可以提醒售卖页面保留证据"
      ],
      "avoid_claims": [
        "把健康监测写成诊断",
        "暗示替代医院检查",
        "扩大注册适用范围"
      ],
      "evidence_level": "官方监管公告",
      "tags": [
        "医疗器械",
        "健康硬件",
        "注册公告",
        "合规边界"
      ],
      "url": "https://www.nmpa.gov.cn/ylqx/ylqxjgdt/index.html"
    },
    {
      "id": "20260708-004",
      "rank": 4,
      "category": "policy",
      "source": "NMPA",
      "source_count": 1,
      "priority": "A",
      "published_at": "2026-07-08T08:00:00+08:00",
      "title": "化妆品新原料和技术要求更新提示功效内容要回到备案与评价证据",
      "summary": "国家药监局化妆品栏目持续更新新原料、备案、监督管理和技术要求信息。抗衰、头皮护理、敏感肌等高流量内容，必须区分化妆品功效宣称、普通美容表达和医疗化表达。",
      "detail": "这是国家药监局化妆品监管信息入口，覆盖新原料、备案、监督抽检和技术规范。对大健康内容来说，它能帮助判断“抗衰”“修护”“头皮健康”等表达是否越过化妆品边界。 行业信号是美妆和大健康内容正在高度融合，但监管仍按化妆品功效评价和标签宣称管理。品牌可以讲清洁、保湿、修护等已评价功效，却不能把产品包装成皮肤病或脱发医学方案。 从业者应把新原料、备案和功效评价资料放在同一审核链条里。消费者内容可做“看懂化妆品功效宣称”，但避免给出诊断和医学建议。",
      "key_points": [
        {
          "label": "这是什么",
          "text": "这是国家药监局化妆品监管信息入口，覆盖新原料、备案、监督抽检和技术规范。对大健康内容来说，它能帮助判断“抗衰”“修护”“头皮健康”等表达是否越过化妆品边界。"
        },
        {
          "label": "行业信号或健康要点",
          "text": "行业信号是美妆和大健康内容正在高度融合，但监管仍按化妆品功效评价和标签宣称管理。品牌可以讲清洁、保湿、修护等已评价功效，却不能把产品包装成皮肤病或脱发医学方案。"
        },
        {
          "label": "从业者或消费者启发",
          "text": "从业者应把新原料、备案和功效评价资料放在同一审核链条里。消费者内容可做“看懂化妆品功效宣称”，但避免给出诊断和医学建议。"
        }
      ],
      "why": "化妆品功效宣称是健康内容高风险区。",
      "media_potential": "适合做《抗衰、头皮、敏感肌内容怎么写才不越界》。",
      "compliance_note": "不得把化妆品写成处理皮肤病、脱发或内分泌问题。",
      "consumer_angle": "消费者可学习区分护肤功效和医学服务。",
      "rewrite_formats": [
        "公众号解读",
        "短视频避坑",
        "合规培训",
        "社群问答"
      ],
      "safe_claims": [
        "可以说明功效评价和备案重要性",
        "可以提醒查看标签和注册备案信息",
        "可以讲日常护理边界"
      ],
      "avoid_claims": [
        "宣称处理脱发",
        "宣称根本解决敏感肌",
        "把新原料等同医学突破"
      ],
      "evidence_level": "官方监管信息",
      "tags": [
        "化妆品",
        "新原料",
        "功效宣称",
        "抗衰"
      ],
      "url": "https://www.nmpa.gov.cn/hzhp/index.html"
    },
    {
      "id": "20260708-005",
      "rank": 5,
      "category": "product",
      "source": "FDA",
      "source_count": 1,
      "priority": "A",
      "published_at": "2026-07-08T08:00:00-04:00",
      "title": "FDA 召回入口继续提示补充剂和食品批次风险需要常态化监测",
      "summary": "FDA 召回、市场撤回和安全警示页面持续更新食品、膳食补充剂、化妆品和个人护理产品风险。跨境健康产品团队应把该页面作为批次、过敏原、污染和标签风险的日常监测入口。",
      "detail": "这是 FDA 的召回与安全警示入口，列出企业自愿召回、市场撤回和安全提示。它适合用于发现补充剂、食品和个护产品的具体批次风险，而不是泛泛证明某一品类不安全。 行业信号是跨境健康产品的合规工作要从上架前延伸到售后和舆情响应。常见风险包括未标示过敏原、微生物污染、异物、标签错误和特定批次质量问题。 从业者可建立每周监测机制，把召回原因、批号、销售渠道和处置建议记录下来。消费者内容可讲“如何查 FDA 召回”，但不能借单个召回否定所有同类产品。",
      "key_points": [
        {
          "label": "这是什么",
          "text": "这是 FDA 的召回与安全警示入口，列出企业自愿召回、市场撤回和安全提示。它适合用于发现补充剂、食品和个护产品的具体批次风险，而不是泛泛证明某一品类不安全。"
        },
        {
          "label": "行业信号或健康要点",
          "text": "行业信号是跨境健康产品的合规工作要从上架前延伸到售后和舆情响应。常见风险包括未标示过敏原、微生物污染、异物、标签错误和特定批次质量问题。"
        },
        {
          "label": "从业者或消费者启发",
          "text": "从业者可建立每周监测机制，把召回原因、批号、销售渠道和处置建议记录下来。消费者内容可讲“如何查 FDA 召回”，但不能借单个召回否定所有同类产品。"
        }
      ],
      "why": "FDA 召回数据是跨境产品风险监测的权威入口。",
      "media_potential": "适合做《跨境保健品团队每周要看的 FDA 召回清单》。",
      "compliance_note": "引用时必须写明品牌、批次、原因和公告日期。",
      "consumer_angle": "消费者可学习核对批号、过敏原和退换货说明。",
      "rewrite_formats": [
        "合规周报",
        "社群提醒",
        "短视频清单",
        "公众号解读"
      ],
      "safe_claims": [
        "可以引用 FDA 页面事实",
        "可以提示核对批次",
        "可以说明召回不等于全品类问题"
      ],
      "avoid_claims": [
        "扩大为全部产品不安全",
        "暗示未召回产品也有问题",
        "替代官方处置建议"
      ],
      "evidence_level": "官方召回数据库",
      "tags": [
        "FDA",
        "召回",
        "膳食补充剂",
        "食品安全"
      ],
      "url": "https://www.fda.gov/safety/recalls-market-withdrawals-safety-alerts"
    },
    {
      "id": "20260708-006",
      "rank": 6,
      "category": "research",
      "source": "FTC",
      "source_count": 1,
      "priority": "A",
      "published_at": "2026-07-08T08:00:00-04:00",
      "title": "FTC 起诉 Amare Global，健康功效和收入展示仍是 MLM 高压线",
      "summary": "FTC 6 月起诉 Amare Global 及相关主体，核心涉及健康功效宣称和商业机会收入表达。对直销和社交零售团队而言，这一案例同时提醒产品话术、见证内容、经销商培训和收入展示都要留证据。",
      "detail": "这是 FTC 针对 Amare Global 的执法信息，涉及健康相关宣称和商业机会营销表达。它不是普通行业争议，而是可作为培训案例的监管动作。 行业信号是监管机构仍会同时审查产品功效和赚钱机会两条线。健康产品若叠加经销商招募，内容风险会从“夸大效果”扩大到“收入展示不典型”和“商业机会误导”。 从业者应复查官网、直播、社群素材和经销商培训课件，删除缺乏证据的健康结论和典型收入暗示。二创适合做合规复盘，不适合做情绪化站队。",
      "key_points": [
        {
          "label": "这是什么",
          "text": "这是 FTC 针对 Amare Global 的执法信息，涉及健康相关宣称和商业机会营销表达。它不是普通行业争议，而是可作为培训案例的监管动作。"
        },
        {
          "label": "行业信号或健康要点",
          "text": "行业信号是监管机构仍会同时审查产品功效和赚钱机会两条线。健康产品若叠加经销商招募，内容风险会从“夸大效果”扩大到“收入展示不典型”和“商业机会误导”。"
        },
        {
          "label": "从业者或消费者启发",
          "text": "从业者应复查官网、直播、社群素材和经销商培训课件，删除缺乏证据的健康结论和典型收入暗示。二创适合做合规复盘，不适合做情绪化站队。"
        }
      ],
      "why": "FTC 执法案例直接对应直销健康内容的两类高风险话术。",
      "media_potential": "适合做《健康产品 + 招募模式最容易踩的两条红线》。",
      "compliance_note": "不得复述未经证实的疗效或收入数字。",
      "consumer_angle": "消费者可理解健康产品营销与商业机会营销需要分别核验。",
      "rewrite_formats": [
        "合规案例复盘",
        "公众号解读",
        "培训课件",
        "短视频拆解"
      ],
      "safe_claims": [
        "可以引用 FTC 行动事实",
        "可以提示健康宣称需证据",
        "可以提示收入表达需真实且典型"
      ],
      "avoid_claims": [
        "站队式渲染",
        "传播未核实疗效",
        "暗示普通人可持续高收入"
      ],
      "evidence_level": "官方执法信息",
      "tags": [
        "FTC",
        "MLM",
        "健康宣称",
        "收入展示"
      ],
      "url": "https://www.ftc.gov/news-events/news/press-releases/2026/06/ftc-sues-stop-amare-global-holdings-misrepresenting-health-benefits-its-dietary-supplements-children"
    },
    {
      "id": "20260708-007",
      "rank": 7,
      "category": "research",
      "source": "FTC",
      "source_count": 1,
      "priority": "A",
      "published_at": "2026-07-07T08:00:00-04:00",
      "title": "FTC 博客重提 Forever Living 案例，收入披露不能用少数成功故事替代",
      "summary": "FTC 商业指导博客围绕 Forever Living 等案例提醒，MLM 收入表达不能用少数成功故事制造普遍可得的印象。对于健康产品经销商内容，产品种草与招募话术必须分开审核。",
      "detail": "这是 FTC 面向企业的商业指导内容，重点在多层级营销和收入展示。它用案例说明，展示高收入、自由生活方式或“副业逆袭”时，必须说明典型结果和重要限制。 行业信号是监管重点不只看公司官网，也会看经销商和推广人员的社媒表达。短视频、直播和私域截图如果持续暗示容易赚钱，同样可能成为风险证据。 从业者应把收入截图、豪车旅行、团队扩张话术纳入素材审查。消费者向内容可以做“如何识别副业赚钱承诺”，但不要把合规提醒写成对具体个人的攻击。",
      "key_points": [
        {
          "label": "这是什么",
          "text": "这是 FTC 面向企业的商业指导内容，重点在多层级营销和收入展示。它用案例说明，展示高收入、自由生活方式或“副业逆袭”时，必须说明典型结果和重要限制。"
        },
        {
          "label": "行业信号或健康要点",
          "text": "行业信号是监管重点不只看公司官网，也会看经销商和推广人员的社媒表达。短视频、直播和私域截图如果持续暗示容易赚钱，同样可能成为风险证据。"
        },
        {
          "label": "从业者或消费者启发",
          "text": "从业者应把收入截图、豪车旅行、团队扩张话术纳入素材审查。消费者向内容可以做“如何识别副业赚钱承诺”，但不要把合规提醒写成对具体个人的攻击。"
        }
      ],
      "why": "收入展示是直销行业长期高风险点。",
      "media_potential": "适合做《副业招募文案里的 5 个合规危险信号》。",
      "compliance_note": "不传播未经证实的收入故事，不使用保证性收入表达。",
      "consumer_angle": "消费者可学会区分产品购买和商业机会判断。",
      "rewrite_formats": [
        "合规培训",
        "短视频拆解",
        "公众号清单",
        "社群提醒"
      ],
      "safe_claims": [
        "可以说收入表达需真实、可证实、非误导",
        "可以提醒展示典型结果",
        "可以建议保留审核记录"
      ],
      "avoid_claims": [
        "保证收入",
        "轻松躺赚",
        "用少数案例代表大多数"
      ],
      "evidence_level": "官方商业指导",
      "tags": [
        "FTC",
        "收入展示",
        "Forever Living",
        "直销合规"
      ],
      "url": "https://www.ftc.gov/business-guidance/blog/2026/06/back-those-earnings-claims-other-lessons-ftcs-labor-task-force-work"
    },
    {
      "id": "20260708-008",
      "rank": 8,
      "category": "industry",
      "source": "Herbalife Investor Relations",
      "source_count": 1,
      "priority": "A",
      "published_at": "2026-07-08T08:00:00-04:00",
      "title": "Herbalife 预告二季度财报，直销健康龙头仍需用财务数据观察基本面",
      "summary": "Herbalife 投资者关系页面预告将发布 2026 年第二季度财务结果。对从业者来说，财报窗口期比传闻更适合观察订单趋势、区域表现、会员活跃度和成本控制。",
      "detail": "这是 Herbalife 官方投资者关系信息，属于企业财务披露预告。它本身不提供业绩结论，但提示市场将在财报和电话会中获得更完整的经营数据。 行业信号是直销健康企业的热度不能只看社媒声量，更要看收入、利润、现金流、区域结构和管理层指引。财报发布前的内容应保持中性，避免提前下判断。 从业者可准备财报阅读框架：看销售趋势、地区差异、产品结构和渠道变化。媒体二创可做“财报看什么”，不要预测股价或承诺行业反转。",
      "key_points": [
        {
          "label": "这是什么",
          "text": "这是 Herbalife 官方投资者关系信息，属于企业财务披露预告。它本身不提供业绩结论，但提示市场将在财报和电话会中获得更完整的经营数据。"
        },
        {
          "label": "行业信号或健康要点",
          "text": "行业信号是直销健康企业的热度不能只看社媒声量，更要看收入、利润、现金流、区域结构和管理层指引。财报发布前的内容应保持中性，避免提前下判断。"
        },
        {
          "label": "从业者或消费者启发",
          "text": "从业者可准备财报阅读框架：看销售趋势、地区差异、产品结构和渠道变化。媒体二创可做“财报看什么”，不要预测股价或承诺行业反转。"
        }
      ],
      "why": "龙头财报是判断直销健康行业温度的重要样本。",
      "media_potential": "适合做《读懂直销健康企业财报：先看这 4 个指标》。",
      "compliance_note": "不做投资建议，不预测股价和未披露业绩。",
      "consumer_angle": "消费者和经销商可理解企业经营数据与产品体验是两类信息。",
      "rewrite_formats": [
        "行业解读",
        "财报清单",
        "公众号分析",
        "社群讨论"
      ],
      "safe_claims": [
        "可以说明财报关注维度",
        "可以引用官方披露时间",
        "可以提醒等待正式数据"
      ],
      "avoid_claims": [
        "提前断言业绩",
        "给出买卖建议",
        "用个别市场传闻替代财报"
      ],
      "evidence_level": "企业官方投资者公告",
      "tags": [
        "Herbalife",
        "财报",
        "直销",
        "营养品"
      ],
      "url": "https://ir.herbalife.com/news-events/press-releases"
    },
    {
      "id": "20260708-009",
      "rank": 9,
      "category": "industry",
      "source": "Zinzino Investor Relations",
      "source_count": 1,
      "priority": "B",
      "published_at": "2026-07-08T08:00:00+02:00",
      "title": "Zinzino 月度销售和季度快报可作为欧洲营养直销增长样本",
      "summary": "Zinzino 投资者关系页面持续披露销售报告和财务信息。该公司以营养、健康测试和订阅型产品为特色，适合观察欧洲直销企业如何把检测、复购和会员体系结合。",
      "detail": "这是 Zinzino 官方投资者关系和新闻入口，提供销售报告、财务发布和企业公告。与二手行业报道相比，官方数据更适合用于判断增长、区域表现和产品策略。 行业信号是营养直销企业越来越强调订阅、检测和个性化健康方案，但这也要求更严格地区分健康管理、营养建议和医学诊断。增长故事如果没有数据支撑，很容易变成招商软文。 从业者可把 Zinzino 作为案例观察复购和服务化表达。二创可拆解“营养订阅模式”，但必须避免把商业模式写成收入保证。",
      "key_points": [
        {
          "label": "这是什么",
          "text": "这是 Zinzino 官方投资者关系和新闻入口，提供销售报告、财务发布和企业公告。与二手行业报道相比，官方数据更适合用于判断增长、区域表现和产品策略。"
        },
        {
          "label": "行业信号或健康要点",
          "text": "行业信号是营养直销企业越来越强调订阅、检测和个性化健康方案，但这也要求更严格地区分健康管理、营养建议和医学诊断。增长故事如果没有数据支撑，很容易变成招商软文。"
        },
        {
          "label": "从业者或消费者启发",
          "text": "从业者可把 Zinzino 作为案例观察复购和服务化表达。二创可拆解“营养订阅模式”，但必须避免把商业模式写成收入保证。"
        }
      ],
      "why": "官方销售披露能帮助判断欧洲直销营养品牌的真实动向。",
      "media_potential": "适合做《营养品直销为什么越来越重视复购和检测服务》。",
      "compliance_note": "不使用夸张收入表达，不把检测服务写成诊断。",
      "consumer_angle": "消费者可理解订阅健康产品时要关注证据、价格和长期适配。",
      "rewrite_formats": [
        "行业案例",
        "公众号分析",
        "商业模式拆解",
        "社群讨论"
      ],
      "safe_claims": [
        "可以引用官方销售披露",
        "可以讨论复购和订阅趋势",
        "可以提醒检测边界"
      ],
      "avoid_claims": [
        "保证经销商收入",
        "把营养检测写成疾病诊断",
        "夸大个性化效果"
      ],
      "evidence_level": "企业官方披露",
      "tags": [
        "Zinzino",
        "欧洲直销",
        "营养订阅",
        "健康测试"
      ],
      "url": "https://www.zinzino.com/site/GB/en-GB/about/press-and-media/investor-relations/"
    },
    {
      "id": "20260708-010",
      "rank": 10,
      "category": "industry",
      "source": "Direct Selling News",
      "source_count": 1,
      "priority": "B",
      "published_at": "2026-07-08T08:00:00-05:00",
      "title": "Direct Selling News 持续追踪 MAKE Wellness，健康社交零售热度仍集中在社区和产品叙事",
      "summary": "Direct Selling News 对 MAKE Wellness 的报道和专题显示，健康社交零售仍在用社区、创始人叙事和新品组合争夺注意力。行业媒体线索有价值，但涉及增长和口碑时仍需回到企业公告和可核验数据。",
      "detail": "这是 Direct Selling News 的行业报道入口，主要用于发现直销和社交零售企业动态。它适合进入候选池，但对具体销量、收入和用户效果仍需二次核验。 行业信号是社交零售新品牌正在把健康、生活方式和社区归属感绑定。内容传播的风险在于把品牌故事写成普遍收入机会，或把用户体验写成医学功效。 从业者可把该线索用于观察新品叙事、社群运营和行业媒体关注点。上线内容应保留“行业媒体报道”属性，不把它写成官方结论。",
      "key_points": [
        {
          "label": "这是什么",
          "text": "这是 Direct Selling News 的行业报道入口，主要用于发现直销和社交零售企业动态。它适合进入候选池，但对具体销量、收入和用户效果仍需二次核验。"
        },
        {
          "label": "行业信号或健康要点",
          "text": "行业信号是社交零售新品牌正在把健康、生活方式和社区归属感绑定。内容传播的风险在于把品牌故事写成普遍收入机会，或把用户体验写成医学功效。"
        },
        {
          "label": "从业者或消费者启发",
          "text": "从业者可把该线索用于观察新品叙事、社群运营和行业媒体关注点。上线内容应保留“行业媒体报道”属性，不把它写成官方结论。"
        }
      ],
      "why": "行业媒体能发现趋势，但不能替代官方数据。",
      "media_potential": "适合做《健康社交零售新品牌为什么都在讲社区故事》。",
      "compliance_note": "需标明为行业媒体报道，关键经营数据应等待官方披露。",
      "consumer_angle": "消费者可从中理解品牌叙事和真实产品证据之间的区别。",
      "rewrite_formats": [
        "行业观察",
        "社群运营拆解",
        "公众号分析",
        "短视频话题"
      ],
      "safe_claims": [
        "可以描述行业媒体关注点",
        "可以讨论社群叙事",
        "可以提醒二次核验"
      ],
      "avoid_claims": [
        "夸大增长",
        "承诺经销商收入",
        "把用户体验当功效证据"
      ],
      "evidence_level": "行业媒体报道",
      "tags": [
        "Direct Selling News",
        "MAKE Wellness",
        "社交零售",
        "社区运营"
      ],
      "url": "https://www.directsellingnews.com/tag/make-wellness/"
    },
    {
      "id": "20260708-011",
      "rank": 11,
      "category": "industry",
      "source": "Business For Home",
      "source_count": 1,
      "priority": "C",
      "published_at": "2026-07-08T08:00:00+02:00",
      "title": "Business For Home 报道 GLP-THREE 获奖，体重管理产品叙事需防止蹭 GLP-1 热点",
      "summary": "Business For Home 报道 THREE International 的 GLP-THREE 获行业奖项。体重管理和 GLP-1 相关叙事近期热度高，但行业媒体和品牌奖项不能替代临床证据或监管批准。",
      "detail": "这是 Business For Home 的行业线索，信息价值在于观察体重管理产品如何借助 GLP-1 话题进入社交零售传播。该来源商业属性较强，适合作为趋势线索，不适合作为功效依据。 行业信号是 GLP-1 药物热度正在外溢到营养品、代餐和体重管理产品叙事。越接近药物概念，越需要避免暗示替代处方药、模拟药物效果或干预肥胖相关疾病。 从业者可借此复查体重管理产品话术，重点删除“类 GLP-1 效果”“不用药也能达到同样结果”等表达。二创应聚焦合规提醒，而非宣传具体奖项。",
      "key_points": [
        {
          "label": "这是什么",
          "text": "这是 Business For Home 的行业线索，信息价值在于观察体重管理产品如何借助 GLP-1 话题进入社交零售传播。该来源商业属性较强，适合作为趋势线索，不适合作为功效依据。"
        },
        {
          "label": "行业信号或健康要点",
          "text": "行业信号是 GLP-1 药物热度正在外溢到营养品、代餐和体重管理产品叙事。越接近药物概念，越需要避免暗示替代处方药、模拟药物效果或干预肥胖相关疾病。"
        },
        {
          "label": "从业者或消费者启发",
          "text": "从业者可借此复查体重管理产品话术，重点删除“类 GLP-1 效果”“不用药也能达到同样结果”等表达。二创应聚焦合规提醒，而非宣传具体奖项。"
        }
      ],
      "why": "GLP-1 热点正在成为体重管理内容的合规雷区。",
      "media_potential": "适合做《营养品能不能蹭 GLP-1 热点：这几句话别说》。",
      "compliance_note": "奖项和行业报道不能作为产品功效证明。",
      "consumer_angle": "消费者可理解体重管理产品不能替代处方药和医生建议。",
      "rewrite_formats": [
        "合规提醒",
        "短视频避坑",
        "公众号解读",
        "选品培训"
      ],
      "safe_claims": [
        "可以说明 GLP-1 是处方药热点",
        "可以提醒体重管理需证据",
        "可以区分营养支持和药物管理"
      ],
      "avoid_claims": [
        "暗示替代 GLP-1 药物",
        "承诺短期体重结果",
        "用奖项证明疗效"
      ],
      "evidence_level": "行业媒体线索，需二次核验",
      "tags": [
        "GLP-1",
        "体重管理",
        "Business For Home",
        "合规风险"
      ],
      "url": "https://www.businessforhome.org/2026/07/three-internationals-glp-three-wins-big-at-2026-nutraingredients-asia-awards/"
    },
    {
      "id": "20260708-012",
      "rank": 12,
      "category": "product",
      "source": "Council for Responsible Nutrition",
      "source_count": 1,
      "priority": "B",
      "published_at": "2026-07-08T08:00:00-04:00",
      "title": "CRN 政策与科学资源提醒膳食补充剂内容应强调补充而非替代",
      "summary": "CRN 作为美国膳食补充剂行业协会，持续发布政策、科学和消费者教育资源。对自媒体来说，这类来源适合辅助理解补充剂边界：补充日常饮食不足，而不是替代均衡饮食、药物或医疗服务。",
      "detail": "这是 CRN 的政策与科学资源入口，适合追踪美国补充剂行业的监管观点和教育材料。协会来源不是监管结论，但能补充产业侧对标签、质量和消费者教育的理解。 行业信号是补充剂内容正在从“单一成分神话”转向“质量、剂量、适用人群和生活方式组合”。如果只讲某个成分能解决所有问题，会同时触碰科学证据和广告合规风险。 从业者可把 CRN 资源作为二级参考，并用 FDA、NIH ODS 或论文进行关键事实验证。消费者内容可做“补充剂不是饭也不是药”的基础科普。",
      "key_points": [
        {
          "label": "这是什么",
          "text": "这是 CRN 的政策与科学资源入口，适合追踪美国补充剂行业的监管观点和教育材料。协会来源不是监管结论，但能补充产业侧对标签、质量和消费者教育的理解。"
        },
        {
          "label": "行业信号或健康要点",
          "text": "行业信号是补充剂内容正在从“单一成分神话”转向“质量、剂量、适用人群和生活方式组合”。如果只讲某个成分能解决所有问题，会同时触碰科学证据和广告合规风险。"
        },
        {
          "label": "从业者或消费者启发",
          "text": "从业者可把 CRN 资源作为二级参考，并用 FDA、NIH ODS 或论文进行关键事实验证。消费者内容可做“补充剂不是饭也不是药”的基础科普。"
        }
      ],
      "why": "协会资源能帮助补充剂内容建立更稳的行业语境。",
      "media_potential": "适合做《膳食补充剂到底补什么：别把它当药也别当万能保险》。",
      "compliance_note": "协会观点需与官方监管或科研证据交叉核验。",
      "consumer_angle": "消费者可理解补充剂应服务于饮食和生活方式，而非替代医疗。",
      "rewrite_formats": [
        "公众号科普",
        "选品清单",
        "社群问答",
        "短视频脚本"
      ],
      "safe_claims": [
        "可以强调补充剂需遵循标签",
        "可以提醒特殊人群咨询专业人士",
        "可以建议关注质量和剂量"
      ],
      "avoid_claims": [
        "宣称替代药物",
        "暗示单一成分包治百病",
        "忽视禁忌和相互作用"
      ],
      "evidence_level": "行业协会资源",
      "tags": [
        "膳食补充剂",
        "CRN",
        "营养",
        "消费者教育"
      ],
      "url": "https://www.crnusa.org/"
    },
    {
      "id": "20260708-013",
      "rank": 13,
      "category": "consumer",
      "source": "CDC",
      "source_count": 1,
      "priority": "A",
      "published_at": "2026-07-08T08:00:00-04:00",
      "title": "CDC 健康体重资料强调运动应与饮食、睡眠和长期习惯一起看",
      "summary": "CDC 健康体重与身体活动资料强调，成年人需要规律身体活动，体重管理也应结合饮食结构、睡眠和可持续习惯。它适合转化为日常健身和减脂内容的安全底稿。",
      "detail": "这是 CDC 面向公众的健康体重和身体活动资料，核心不是承诺短期变瘦，而是解释规律活动如何支持体重、心肺、代谢和日常功能。资料强调循序渐进和长期坚持。 健康要点是体重管理不能只靠短期挑战或单一产品。运动建议要结合个人基础、慢性病情况和可持续安排，力量训练、有氧活动和减少久坐都可以成为内容角度。 消费者可把目标拆成每周计划和每日小行动，不必追求极端训练。自媒体改写时应避免“几天瘦多少”“局部减脂”等说法，重点做可执行清单。",
      "key_points": [
        {
          "label": "这是什么",
          "text": "这是 CDC 面向公众的健康体重和身体活动资料，核心不是承诺短期变瘦，而是解释规律活动如何支持体重、心肺、代谢和日常功能。资料强调循序渐进和长期坚持。"
        },
        {
          "label": "行业信号或健康要点",
          "text": "健康要点是体重管理不能只靠短期挑战或单一产品。运动建议要结合个人基础、慢性病情况和可持续安排，力量训练、有氧活动和减少久坐都可以成为内容角度。"
        },
        {
          "label": "从业者或消费者启发",
          "text": "消费者可把目标拆成每周计划和每日小行动，不必追求极端训练。自媒体改写时应避免“几天瘦多少”“局部减脂”等说法，重点做可执行清单。"
        }
      ],
      "why": "CDC 是健身、减脂和体重管理内容的高可信基础来源。",
      "media_potential": "适合做《普通人每周运动怎么安排：比短期冲刺更靠谱的清单》。",
      "compliance_note": "不承诺减重速度，不替代专业建议。",
      "consumer_angle": "消费者可从每周活动量、力量训练和减少久坐开始。",
      "rewrite_formats": [
        "公众号科普",
        "短视频脚本",
        "小红书清单",
        "社群打卡"
      ],
      "safe_claims": [
        "可以引用 CDC 身体活动建议",
        "可以鼓励循序渐进",
        "可以提醒特殊人群咨询专业人士"
      ],
      "avoid_claims": [
        "短期体重结果承诺",
        "局部减脂保证",
        "运动替代专业干预"
      ],
      "evidence_level": "官方公共卫生指南",
      "tags": [
        "运动",
        "体重管理",
        "减脂",
        "健身"
      ],
      "url": "https://www.cdc.gov/healthy-weight-growth/physical-activity/index.html"
    },
    {
      "id": "20260708-014",
      "rank": 14,
      "category": "consumer",
      "source": "Johns Hopkins Medicine",
      "source_count": 1,
      "priority": "A",
      "published_at": "2026-07-08T08:00:00-04:00",
      "title": "Johns Hopkins 谈运动与睡眠，健身内容可从时间安排切入但不能神化最佳时段",
      "summary": "Johns Hopkins Medicine 解释运动与睡眠质量的关系，并提醒部分人太晚运动可能影响休息。这个选题适合做成“早练、午练、晚练怎么选”的实用内容，但应强调个人作息、可坚持性和安全性。",
      "detail": "这是 Johns Hopkins 面向消费者的健康文章，讨论运动如何帮助睡眠，以及运动时间需要根据个体反应调整。它提供的是生活方式参考，不是对所有人统一的训练处方。 健康要点是健身效果不只取决于动作和强度，也受睡眠、作息和坚持度影响。对多数普通人来说，能长期坚持、不过度影响睡眠和工作，比追求所谓最佳时段更重要。 消费者可用它判断自己适合早练还是晚练，并观察睡眠和疲劳反应。二创适合做问答和清单，避免说某个时间段一定燃脂更快。",
      "key_points": [
        {
          "label": "这是什么",
          "text": "这是 Johns Hopkins 面向消费者的健康文章，讨论运动如何帮助睡眠，以及运动时间需要根据个体反应调整。它提供的是生活方式参考，不是对所有人统一的训练处方。"
        },
        {
          "label": "行业信号或健康要点",
          "text": "健康要点是健身效果不只取决于动作和强度，也受睡眠、作息和坚持度影响。对多数普通人来说，能长期坚持、不过度影响睡眠和工作，比追求所谓最佳时段更重要。"
        },
        {
          "label": "从业者或消费者启发",
          "text": "消费者可用它判断自己适合早练还是晚练，并观察睡眠和疲劳反应。二创适合做问答和清单，避免说某个时间段一定燃脂更快。"
        }
      ],
      "why": "运动和睡眠联动是高传播度且合规可控的消费者选题。",
      "media_potential": "适合做《早练还是晚练：先看你睡得好不好》。",
      "compliance_note": "避免宣称特定时段一定减脂或改善疾病。",
      "consumer_angle": "消费者可根据作息、睡眠和可坚持性选择运动时间。",
      "rewrite_formats": [
        "公众号科普",
        "短视频问答",
        "小红书清单",
        "社群讨论"
      ],
      "safe_claims": [
        "可以讨论作息和坚持度",
        "可以提醒晚间高强度运动影响睡眠",
        "可以建议观察个人反应"
      ],
      "avoid_claims": [
        "神化黄金燃脂时间",
        "保证同样训练效果",
        "替代个体化医学建议"
      ],
      "evidence_level": "医学机构消费者健康文章",
      "tags": [
        "运动",
        "生物钟",
        "睡眠",
        "健身"
      ],
      "url": "https://www.hopkinsmedicine.org/health/wellness-and-prevention/exercising-for-better-sleep"
    },
    {
      "id": "20260708-015",
      "rank": 15,
      "category": "consumer",
      "source": "Harvard Health Publishing",
      "source_count": 1,
      "priority": "A",
      "published_at": "2026-04-01T08:00:00-04:00",
      "title": "哈佛健康将睡眠和血糖放在一起讨论，睡眠内容可连接代谢但要避免医学化",
      "summary": "Harvard Health 2026 年 4 月文章讨论睡眠时长与血糖调节之间的关系。对健康自媒体来说，这是把睡眠、饮食和代谢健康连接起来的好素材，但表达应停留在生活方式风险和健康素养，不替代糖尿病管理。",
      "detail": "这是 Harvard Health 面向公众的睡眠与代谢健康文章，介绍一项 2026 年研究中睡眠时长与胰岛素敏感性的关联。文章适合做日常健康教育，而不是给出疾病处理方案。 健康要点是睡眠不只是精神状态问题，也会影响食欲、活动量和代谢相关行为。对普通消费者，规律作息、减少熬夜和配合饮食运动，比依赖单一补充剂更稳。 消费者可把睡眠列入体重和血糖管理的基础习惯。二创可做“睡不好为什么更想吃甜食”的科普，但要提醒糖尿病患者遵医嘱。",
      "key_points": [
        {
          "label": "这是什么",
          "text": "这是 Harvard Health 面向公众的睡眠与代谢健康文章，介绍一项 2026 年研究中睡眠时长与胰岛素敏感性的关联。文章适合做日常健康教育，而不是给出疾病处理方案。"
        },
        {
          "label": "行业信号或健康要点",
          "text": "健康要点是睡眠不只是精神状态问题，也会影响食欲、活动量和代谢相关行为。对普通消费者，规律作息、减少熬夜和配合饮食运动，比依赖单一补充剂更稳。"
        },
        {
          "label": "从业者或消费者启发",
          "text": "消费者可把睡眠列入体重和血糖管理的基础习惯。二创可做“睡不好为什么更想吃甜食”的科普，但要提醒糖尿病患者遵医嘱。"
        }
      ],
      "why": "睡眠是连接减脂、情绪和代谢的高价值素材。",
      "media_potential": "适合做《睡不好不只是困：它可能影响你怎么吃和怎么动》。",
      "compliance_note": "不宣称睡眠习惯能处理糖尿病或替代药物。",
      "consumer_angle": "消费者可从固定起床时间、减少熬夜和睡前习惯入手。",
      "rewrite_formats": [
        "公众号科普",
        "短视频脚本",
        "小红书清单",
        "社群问答"
      ],
      "safe_claims": [
        "可以说睡眠与代谢行为相关",
        "可以建议规律作息",
        "可以提醒患者遵医嘱"
      ],
      "avoid_claims": [
        "睡眠搞定糖尿病",
        "褪黑素解决血糖",
        "单一习惯替代综合管理"
      ],
      "evidence_level": "医学机构消费者健康文章",
      "tags": [
        "睡眠",
        "血糖",
        "代谢",
        "体重管理"
      ],
      "url": "https://www.health.harvard.edu/sleep/seven-hours-of-sleep-linked-to-better-blood-sugar-regulation"
    },
    {
      "id": "20260708-016",
      "rank": 16,
      "category": "consumer",
      "source": "Mayo Clinic",
      "source_count": 1,
      "priority": "A",
      "published_at": "2026-07-08T08:00:00-05:00",
      "title": "Mayo Clinic 解读 GLP-1 药物期待，体重管理内容更要区分药物、饮食和生活方式",
      "summary": "Mayo Clinic 关于 GLP-1 的消费者健康内容提醒，相关药物有明确适应证、风险和医学管理要求。大健康自媒体可以解释体重管理趋势，但不能把营养品、课程或普通食品包装成药物替代方案。",
      "detail": "这是 Mayo Clinic 面向公众的 GLP-1 相关健康资料，核心是帮助读者理解药物期待、适用边界和需要专业管理的原因。它不支持把 GLP-1 热度泛化到所有减重产品。 健康要点是体重管理正在进入药物、饮食、运动和行为支持并行的阶段。越热门的概念越容易被营销滥用，尤其是营养品借药物名词暗示同等效果。 消费者应把处方药问题交给医生，把日常饮食、运动和睡眠作为基础。二创适合做“GLP-1 热点下普通人该知道什么”，避免推荐具体药物或替代品。",
      "key_points": [
        {
          "label": "这是什么",
          "text": "这是 Mayo Clinic 面向公众的 GLP-1 相关健康资料，核心是帮助读者理解药物期待、适用边界和需要专业管理的原因。它不支持把 GLP-1 热度泛化到所有减重产品。"
        },
        {
          "label": "行业信号或健康要点",
          "text": "健康要点是体重管理正在进入药物、饮食、运动和行为支持并行的阶段。越热门的概念越容易被营销滥用，尤其是营养品借药物名词暗示同等效果。"
        },
        {
          "label": "从业者或消费者启发",
          "text": "消费者应把处方药问题交给医生，把日常饮食、运动和睡眠作为基础。二创适合做“GLP-1 热点下普通人该知道什么”，避免推荐具体药物或替代品。"
        }
      ],
      "why": "GLP-1 是减重内容热词，也是合规高风险词。",
      "media_potential": "适合做《GLP-1 很火，但普通营养品不能这么蹭热点》。",
      "compliance_note": "不得推荐处方药，不暗示食品或补充剂有同等作用。",
      "consumer_angle": "消费者可理解药物管理、生活方式和营养支持的边界。",
      "rewrite_formats": [
        "公众号科普",
        "短视频避坑",
        "社群问答",
        "选品培训"
      ],
      "safe_claims": [
        "可以强调需专业医疗管理",
        "可以区分药物和营养支持",
        "可以提醒长期生活方式仍重要"
      ],
      "avoid_claims": [
        "推荐处方药",
        "宣称营养品替代 GLP-1",
        "承诺短期体重结果"
      ],
      "evidence_level": "医学机构消费者健康资料",
      "tags": [
        "GLP-1",
        "减重",
        "体重管理",
        "营养合规"
      ],
      "url": "https://www.mayoclinic.org/diseases-conditions/obesity/in-depth/glp-1s/art-20531569"
    },
    {
      "id": "20260708-017",
      "rank": 17,
      "category": "consumer",
      "source": "NIH National Institute on Aging",
      "source_count": 1,
      "priority": "A",
      "published_at": "2026-07-08T08:00:00-04:00",
      "title": "NIA 老年营养资料适合转化为中老年健康内容的稳定底稿",
      "summary": "美国国家老龄研究所的老年营养资料强调均衡饮食、蛋白质、膳食纤维、水分和食品安全等基础问题。中老年健康内容应把重点放在日常可执行习惯，而不是单一补品或抗衰神话。",
      "detail": "这是 NIA 面向老年人和照护者的健康饮食资料，覆盖营养需求、饮食计划和健康老龄化基础。它适合作为中老年健康科普底稿。 健康要点是老年营养不只是补钙或吃保健品，还包括总能量、蛋白质质量、蔬果全谷、饮水、咀嚼吞咽和慢病用药背景。内容需要避免把复杂问题简化成一种产品。 消费者可把它改成“爸妈一日三餐检查清单”。从业者可用来设计低风险教育内容，但特殊疾病、营养不良或用药人群要建议咨询医生或营养师。",
      "key_points": [
        {
          "label": "这是什么",
          "text": "这是 NIA 面向老年人和照护者的健康饮食资料，覆盖营养需求、饮食计划和健康老龄化基础。它适合作为中老年健康科普底稿。"
        },
        {
          "label": "行业信号或健康要点",
          "text": "健康要点是老年营养不只是补钙或吃保健品，还包括总能量、蛋白质质量、蔬果全谷、饮水、咀嚼吞咽和慢病用药背景。内容需要避免把复杂问题简化成一种产品。"
        },
        {
          "label": "从业者或消费者启发",
          "text": "消费者可把它改成“爸妈一日三餐检查清单”。从业者可用来设计低风险教育内容，但特殊疾病、营养不良或用药人群要建议咨询医生或营养师。"
        }
      ],
      "why": "中老年健康是高需求赛道，官方老龄资料能降低夸大风险。",
      "media_potential": "适合做《给爸妈的饮食清单：比盲目买补品更先看这些》。",
      "compliance_note": "不把单一营养素或补品写成抗衰解决方案。",
      "consumer_angle": "中老年消费者可关注蛋白质、蔬果、饮水和食品安全。",
      "rewrite_formats": [
        "公众号科普",
        "小红书清单",
        "短视频脚本",
        "社群问答"
      ],
      "safe_claims": [
        "可以建议均衡饮食",
        "可以提醒照护者关注进食困难",
        "可以建议特殊情况求助专业人士"
      ],
      "avoid_claims": [
        "补品逆转衰老",
        "一种营养素解决所有问题",
        "替代慢病管理"
      ],
      "evidence_level": "官方老龄健康资料",
      "tags": [
        "中老年健康",
        "营养",
        "健康老龄化",
        "蛋白质"
      ],
      "url": "https://www.nia.nih.gov/health/healthy-eating-nutrition-and-diet"
    },
    {
      "id": "20260708-018",
      "rank": 18,
      "category": "consumer",
      "source": "CDC",
      "source_count": 1,
      "priority": "A",
      "published_at": "2026-07-08T08:00:00-04:00",
      "title": "CDC 压力管理资料强调睡眠、活动和求助意识，情绪内容不要产品化",
      "summary": "CDC 心理健康生活资料强调，压力管理可从睡眠、身体活动、建立小目标和寻求支持开始。情绪压力是高需求主题，但自媒体表达必须避开“产品解决焦虑抑郁”等医疗化承诺。",
      "detail": "这是 CDC 面向公众的心理健康和压力管理资料，提供生活方式支持和求助意识。它适合做基础科普，不适合包装成课程、食品或补充剂的疗效证明。 健康要点是压力管理通常需要睡眠、运动、社交支持和专业帮助共同作用。内容可以讲行动清单和识别求助信号，但不能把严重心理症状简化成靠自律或消费解决。 消费者可从固定作息、短时活动和向可信赖的人求助开始。自媒体二创应把边界写清：严重、持续或影响生活的症状需要专业支持。",
      "key_points": [
        {
          "label": "这是什么",
          "text": "这是 CDC 面向公众的心理健康和压力管理资料，提供生活方式支持和求助意识。它适合做基础科普，不适合包装成课程、食品或补充剂的疗效证明。"
        },
        {
          "label": "行业信号或健康要点",
          "text": "健康要点是压力管理通常需要睡眠、运动、社交支持和专业帮助共同作用。内容可以讲行动清单和识别求助信号，但不能把严重心理症状简化成靠自律或消费解决。"
        },
        {
          "label": "从业者或消费者启发",
          "text": "消费者可从固定作息、短时活动和向可信赖的人求助开始。自媒体二创应把边界写清：严重、持续或影响生活的症状需要专业支持。"
        }
      ],
      "why": "情绪压力是高流量但高合规敏感的健康主题。",
      "media_potential": "适合做《压力大先别急着买产品：先检查睡眠、活动和求助信号》。",
      "compliance_note": "不得宣称食品、补充剂或课程可处理焦虑抑郁。",
      "consumer_angle": "消费者可学习生活方式支持和何时寻求专业帮助。",
      "rewrite_formats": [
        "公众号科普",
        "短视频脚本",
        "小红书清单",
        "社群问答"
      ],
      "safe_claims": [
        "可以建议规律睡眠",
        "可以鼓励身体活动",
        "可以提醒寻求专业帮助"
      ],
      "avoid_claims": [
        "产品解决焦虑抑郁",
        "课程保证疗愈",
        "替代心理或医学诊疗"
      ],
      "evidence_level": "官方公共卫生科普",
      "tags": [
        "情绪压力",
        "睡眠",
        "运动",
        "心理健康"
      ],
      "url": "https://www.cdc.gov/mental-health/living-with/index.html"
    },
    {
      "id": "20260708-019",
      "rank": 19,
      "category": "research",
      "source": "NIH ODS",
      "source_count": 1,
      "priority": "A",
      "published_at": "2026-07-08T08:00:00-04:00",
      "title": "NIH ODS 膳食补充剂资料库适合核验成分证据、剂量和安全边界",
      "summary": "NIH ODS 膳食补充剂资料库提供维生素、矿物质、草本和其他成分的事实页。健康内容团队在写益生菌、镁、维生素 D、鱼油等热门成分前，应先核对证据强度、剂量范围和相互作用。",
      "detail": "这是 NIH ODS 的膳食补充剂事实页入口，面向消费者和专业人士提供成分用途、安全性、摄入量和证据信息。它比品牌白皮书更适合作为基础核验来源。 行业信号是补充剂内容不能只看成分热度，还要看适用人群、上限、药物相互作用和研究质量。很多成分可以作为营养支持，但不能自动转化为疾病干预结论。 从业者可把 ODS 资料库作为成分文案审核第一步。消费者内容可做“买补充剂前先查哪些信息”，尤其提醒孕期、慢病和用药人群谨慎。",
      "key_points": [
        {
          "label": "这是什么",
          "text": "这是 NIH ODS 的膳食补充剂事实页入口，面向消费者和专业人士提供成分用途、安全性、摄入量和证据信息。它比品牌白皮书更适合作为基础核验来源。"
        },
        {
          "label": "行业信号或健康要点",
          "text": "行业信号是补充剂内容不能只看成分热度，还要看适用人群、上限、药物相互作用和研究质量。很多成分可以作为营养支持，但不能自动转化为疾病干预结论。"
        },
        {
          "label": "从业者或消费者启发",
          "text": "从业者可把 ODS 资料库作为成分文案审核第一步。消费者内容可做“买补充剂前先查哪些信息”，尤其提醒孕期、慢病和用药人群谨慎。"
        }
      ],
      "why": "ODS 是补充剂证据核验的权威公共来源。",
      "media_potential": "适合做《热门补充剂怎么查证据：先看 NIH ODS 这几项》。",
      "compliance_note": "不把成分事实页改写成具体产品功效承诺。",
      "consumer_angle": "消费者可学习看剂量、上限、安全性和相互作用。",
      "rewrite_formats": [
        "公众号科普",
        "选品清单",
        "短视频教程",
        "合规培训"
      ],
      "safe_claims": [
        "可以引用 ODS 事实页",
        "可以提醒剂量和安全上限",
        "可以建议用药人群咨询专业人士"
      ],
      "avoid_claims": [
        "宣称成分处理疾病",
        "忽视相互作用",
        "用品牌资料替代公共证据"
      ],
      "evidence_level": "官方膳食补充剂事实资料库",
      "tags": [
        "NIH ODS",
        "膳食补充剂",
        "成分证据",
        "安全性"
      ],
      "url": "https://ods.od.nih.gov/factsheets/list-all/"
    },
    {
      "id": "20260708-020",
      "rank": 20,
      "category": "consumer",
      "source": "WHO",
      "source_count": 1,
      "priority": "A",
      "published_at": "2026-07-08T08:00:00+08:00",
      "title": "WHO 健康饮食事实页仍是营养内容的基础引用：少盐、控糖、吃够蔬果",
      "summary": "WHO 健康饮食事实页强调蔬果、全谷、豆类、坚果、限制游离糖、盐和不健康脂肪等基础原则。它适合做日常营养内容底稿，尤其能抵消极端饮食和单一补品叙事。",
      "detail": "这是 WHO 面向全球公众的健康饮食事实页，提供成年人和儿童饮食的基础原则。资料强调整体膳食模式，而不是某个万能食物或单一营养素。 健康要点是可靠营养建议往往朴素但可持续：多样化食物、足量蔬果、减少高盐高糖和反式脂肪。相比追逐新概念，基础饮食结构更适合长期健康教育。 消费者可用它检查一日三餐，而不是急着购买复杂补充方案。二创可做“真正靠谱的饮食建议为什么都很普通”，避免把饮食建议写成疾病处理。",
      "key_points": [
        {
          "label": "这是什么",
          "text": "这是 WHO 面向全球公众的健康饮食事实页，提供成年人和儿童饮食的基础原则。资料强调整体膳食模式，而不是某个万能食物或单一营养素。"
        },
        {
          "label": "行业信号或健康要点",
          "text": "健康要点是可靠营养建议往往朴素但可持续：多样化食物、足量蔬果、减少高盐高糖和反式脂肪。相比追逐新概念，基础饮食结构更适合长期健康教育。"
        },
        {
          "label": "从业者或消费者启发",
          "text": "消费者可用它检查一日三餐，而不是急着购买复杂补充方案。二创可做“真正靠谱的饮食建议为什么都很普通”，避免把饮食建议写成疾病处理。"
        }
      ],
      "why": "WHO 事实页是营养饮食内容的高可靠底层来源。",
      "media_potential": "适合做《靠谱养生先看餐盘：少盐控糖吃够蔬果》。",
      "compliance_note": "不得把健康饮食写成处理具体疾病的方案。",
      "consumer_angle": "消费者可从蔬果、全谷、控盐控糖和少反式脂肪开始。",
      "rewrite_formats": [
        "公众号科普",
        "小红书清单",
        "短视频脚本",
        "社群打卡"
      ],
      "safe_claims": [
        "可以引用 WHO 健康饮食原则",
        "可以建议逐步改善饮食结构",
        "可以提醒个体化营养需求"
      ],
      "avoid_claims": [
        "单一食物解决疾病",
        "极端断食适合所有人",
        "补品替代均衡饮食"
      ],
      "evidence_level": "国际公共卫生事实页",
      "tags": [
        "营养饮食",
        "控盐",
        "控糖",
        "蔬果"
      ],
      "url": "https://www.who.int/news-room/fact-sheets/detail/healthy-diet"
    }
  ],
  "date": "2026-07-08",
  "brief_title": "2026/07/08 大健康与直销行业每日简报"
}
